simpletimerbank/__init__.py
simpletimerbank/main.py
simpletimerbank/assets/__init__.py
simpletimerbank/assets/sounds/__init__.py
simpletimerbank/assets/sounds/notification.wav
simpletimerbank/core/__init__.py
simpletimerbank/core/app_state.py
simpletimerbank/core/countdown_timer.py
simpletimerbank/core/notification_service.py
simpletimerbank/core/persistence.py
simpletimerbank/core/time_balance.py
simpletimerbank/core/time_bank.py
simpletimerbank/gui/__init__.py
simpletimerbank/gui/main_window.py
simpletimerbank/gui/widgets/__init__.py
simpletimerbank/gui/widgets/time_display.py
simpletimerbank/gui/widgets/time_edit.py
simpletimerbank/gui/widgets/timer_control.py
timerbank-1.0.0.dist-info/METADATA
timerbank-1.0.0.dist-info/WHEEL
timerbank-1.0.0.dist-info/entry_points.txt
timerbank-1.0.0.dist-info/licenses/LICENSE
timerbank-1.0.0.dist-info/RECORD
