Metadata-Version: 2.4
Name: TimerBank
Version: 1.0.0
Summary: A desktop application for managing your personal "free time" bank.
Project-URL: Homepage, https://supersheepbear.github.io/SimpleTimerBank/
Project-URL: Repository, https://github.com/supersheepbear/SimpleTimerBank
Project-URL: Documentation, https://supersheepbear.github.io/SimpleTimerBank/
Author-email: supersheepbear <supersheepbear@gmail.com>
License-File: LICENSE
Keywords: python
Classifier: Intended Audience :: Developers
Classifier: Programming Language :: Python
Classifier: Programming Language :: Python :: 3
Classifier: Programming Language :: Python :: 3.9
Classifier: Programming Language :: Python :: 3.10
Classifier: Programming Language :: Python :: 3.11
Classifier: Programming Language :: Python :: 3.12
Classifier: Programming Language :: Python :: 3.13
Classifier: Topic :: Software Development :: Libraries :: Python Modules
Requires-Python: <4.0,>=3.9
Requires-Dist: playsound==1.2.2
Requires-Dist: plyer>=2.1.0
Requires-Dist: pyside6>=6.6.0
